wize_mcp/__init__.py
wize_mcp/config.py
wize_mcp/main.py
wize_mcp/test.py
wize_mcp/api/__init__.py
wize_mcp/api/client.py
wize_mcp/tools/base.py
wize_mcp/tools/result.py
wize_mcp/tools/assets/__init__.py
wize_mcp/tools/assets/get_assets.py
wize_mcp/tools/categories/__init__.py
wize_mcp/tools/categories/get_categories.py
wize_mcp/tools/employees/__init__.py
wize_mcp/tools/employees/create_employee.py
wize_mcp/tools/employees/create_employee_address.py
wize_mcp/tools/employees/create_employee_asset.py
wize_mcp/tools/employees/create_order_for_employee.py
wize_mcp/tools/employees/get_employee_addresses.py
wize_mcp/tools/employees/get_employee_user.py
wize_mcp/tools/employees/get_employees.py
wize_mcp/tools/employees/update_employee.py
wize_mcp/tools/employees/update_employee_address.py
wize_mcp/tools/invites/__init__.py
wize_mcp/tools/invites/create_invite.py
wize_mcp/tools/offboards/__init__.py
wize_mcp/tools/offboards/create_offboard.py
wize_mcp/tools/offboards/get_offboards.py
wize_mcp/tools/offices/__init__.py
wize_mcp/tools/offices/create_order_for_office.py
wize_mcp/tools/offices/get_offices.py
wize_mcp/tools/orders/__init__.py
wize_mcp/tools/orders/get_order_products.py
wize_mcp/tools/orders/get_order_shipments.py
wize_mcp/tools/orders/get_orders.py
wize_mcp/tools/products/__init__.py
wize_mcp/tools/products/get_products.py
wize_mcp/tools/self/__init__.py
wize_mcp/tools/self/get_self.py
wize_mcp/tools/users/__init__.py
wize_mcp/tools/users/create_user.py
wize_mcp/tools/warehouses/__init__.py
wize_mcp/tools/warehouses/create_order_for_warehouse.py
wize_mcp/tools/warehouses/get_warehouses.py
wize_mcp-0.1.6.dist-info/METADATA
wize_mcp-0.1.6.dist-info/WHEEL
wize_mcp-0.1.6.dist-info/entry_points.txt
wize_mcp-0.1.6.dist-info/RECORD
