Metadata-Version: 2.4
Name: wize-mcp
Version: 0.1.6
Summary: MCP integration for Workwize
Author-email: Raúl López <hi@raullg.com>
Requires-Python: >=3.11
Requires-Dist: httpx>=0.28.1
Requires-Dist: mcp>=1.6.0
Requires-Dist: pydantic>=2.11.3
Requires-Dist: python-dotenv
